visound/__init__.py
visound/cli.py
visound/core/TraversalMode.py
visound/core/__init__.py
visound/core/sonify.py
visound-0.1.6.dist-info/licenses/LICENSE
visound-0.1.6.dist-info/METADATA
visound-0.1.6.dist-info/WHEEL
visound-0.1.6.dist-info/entry_points.txt
visound-0.1.6.dist-info/top_level.txt
visound-0.1.6.dist-info/RECORD
