Metadata-Version: 2.4
Name: ViSound
Version: 0.1.6
Summary: A library to sonify images using Python
Author-email: Dheeraj Vittal Shenoy <dheerajshenoy22@email.com>
Project-URL: Homepage, https://github.com/dheerajshenoy/ViSound
License-File: LICENSE
Requires-Dist: numpy
Requires-Dist: opencv-python
Requires-Dist: sounddevice
Requires-Dist: soundfile
Dynamic: license-file
